pykeybase/__init__.py
pykeybase/async_chat.py
pykeybase/bot.py
pykeybase/chat.py
pykeybase/kbfs.py
pykeybase/team.py
pykeybase/wallet.py
pykeybase-0.5.3.dist-info/LICENSE.md
pykeybase-0.5.3.dist-info/METADATA
pykeybase-0.5.3.dist-info/WHEEL
pykeybase-0.5.3.dist-info/top_level.txt
pykeybase-0.5.3.dist-info/RECORD
