Metadata-Version: 2.2
Name: pykeybase
Version: 0.5.3
Summary: Python client for keybase
Author: ['Samuel Hofius', 'Jesse Cooper']
Author-email: jesse_cooper@codeholics.com
License: BSD
Classifier: Development Status :: 3 - Alpha
Classifier: Intended Audience :: Developers
Classifier: Programming Language :: Python :: 3
License-File: LICENSE.md
Dynamic: author
Dynamic: author-email
Dynamic: classifier
Dynamic: description
Dynamic: description-content-type
Dynamic: keywords
Dynamic: license
Dynamic: summary
